[{
    "_notes": [],
    "group_ve9cv03/Site_type": "housing__habitacional",
    "_xform_id_string": "apHdoBqmXMLQkiok6Pdjea",
    "_tags": [],
    "group_ve9cv03/Current_use": "agriculture__agricultura",
    "meta/instanceID": "uuid:cea622c0-e7f2-4f2b-8711-eb52df609e5a",
    "group_ve9cv03/Current_vegetation": "grassland__pastizales",
    "Recorded_by": "Lucy Gill",
    "group_ve9cv03/Parallel_visibility": "medium",
    "Enter_date_and_time_of_discovery": "2019-07-01T15:16:00.000-05:00",
    "group_ve9cv03/Non_human_disturbance": "vegetaci_n",
    "group_ve9cv03/Conservation": "very_disturbed",
    "start": "2021-03-29T19:53:00.687-05:00",
    "group_ve9cv03/Surface_soil": "_limo _arcilla",
    "_attachments": [{
      "mimetype": "image/jpeg",
      "download_small_url": "https://kc.kobotoolbox.org/media/small?media_file=dariengap2021%2Fattachments%2Fbf9676788f314c00a984ea8002333ac1%2Fcea622c0-e7f2-4f2b-8711-eb52df609e5a%2F13-15_48_19-19_59_26.jpg",
      "download_large_url": "https://kc.kobotoolbox.org/media/large?media_file=dariengap2021%2Fattachments%2Fbf9676788f314c00a984ea8002333ac1%2Fcea622c0-e7f2-4f2b-8711-eb52df609e5a%2F13-15_48_19-19_59_26.jpg",
      "download_url": "https://kc.kobotoolbox.org/media/original?media_file=dariengap2021%2Fattachments%2Fbf9676788f314c00a984ea8002333ac1%2Fcea622c0-e7f2-4f2b-8711-eb52df609e5a%2F13-15_48_19-19_59_26.jpg",
      "filename": "dariengap2021/attachments/bf9676788f314c00a984ea8002333ac1/cea622c0-e7f2-4f2b-8711-eb52df609e5a/13-15_48_19-19_59_26.jpg",
      "instance": 90569847,
      "download_medium_url": "https://kc.kobotoolbox.org/media/medium?media_file=dariengap2021%2Fattachments%2Fbf9676788f314c00a984ea8002333ac1%2Fcea622c0-e7f2-4f2b-8711-eb52df609e5a%2F13-15_48_19-19_59_26.jpg",
      "id": 32009892,
      "xform": 639284
    }],
    "Edited_date_and_time": "2019-07-16T15:08:00.000-05:00",
    "_status": "submitted_via_web",
    "formhub/uuid": "bf9676788f314c00a984ea8002333ac1",
    "username": "username not found",
    "_validation_status": {},
    "_uuid": "cea622c0-e7f2-4f2b-8711-eb52df609e5a",
    "Record_your_current_location": "8.06163 -78.363107 0 0",
    "_submitted_by": null,
    "end": "2021-03-29T20:01:26.494-05:00",
    "group_ve9cv03/Site_name": "Ch6?",
    "What_did_you_find": "site",
    "__version__": "vJLQEGi5dLMUNuBsjGNRmu",
    "Edited_by": "1503628_CAL",
    "group_ve9cv03/Ground_visibility": "medium",
    "group_ve9cv03/group_qn6ym49": [{
      "group_ve9cv03/group_qn6ym49/Other_items_present_or_absent": "ceramic groundstone mound loose_stones"
    }],
    "_submission_time": "2021-03-30T01:02:51",
    "group_ve9cv03/Description_001": "Sediment is clayey silt. Is a shell mound very nearby, took sample. Next to a modern house but woman says it is not modern.",
    "_geolocation": [
      8.06163,
      -78.363107
    ],
    "deviceid": "ee.kobotoolbox.org:SamGhFwda0v8M1oh",
    "group_ve9cv03/Anthropological_disturbance": "other__otro",
    "_id": 90569847,
    "group_qk9bw75": [{
      "group_qk9bw75/Photo_1": "13-15_48_19-19_59_26.jpg"
    }]
  },
  {
    "username": "username not found",
    "_notes": [],
    "meta/instanceID": "uuid:4f72a6a3-ccc1-47a4-bb58-db47afdc5624",
    "end": "2021-03-29T19:06:22.987-05:00",
    "_submission_time": "2021-03-30T00:07:45",
    "_validation_status": {},
    "_uuid": "4f72a6a3-ccc1-47a4-bb58-db47afdc5624",
    "_tags": [],
    "_attachments": [],
    "start": "2021-03-29T19:05:23.986-05:00",
    "_submitted_by": null,
    "_geolocation": [
      null,
      null
    ],
    "deviceid": "ee.kobotoolbox.org:SamGhFwda0v8M1oh",
    "_xform_id_string": "apHdoBqmXMLQkiok6Pdjea",
    "_status": "submitted_via_web",
    "_id": 90567843,
    "__version__": "vJLQEGi5dLMUNuBsjGNRmu",
    "formhub/uuid": "bf9676788f314c00a984ea8002333ac1"
  },
  {
    "_notes": [],
    "_tags": [],
    "_xform_id_string": "apHdoBqmXMLQkiok6Pdjea",
    "meta/instanceID": "uuid:eb6d25d3-2255-4288-83a0-271c9a2760f9",
    "Recorded_by": "Piperno 1994",
    "end": "2021-03-29T18:14:56.687-05:00",
    "Enter_date_and_time_of_discovery": "2019-07-16T15:07:00.000-05:00",
    "start": "2021-03-29T18:09:49.779-05:00",
    "_geolocation": [
      7.90420277777777,
      -77.6426388888889
    ],
    "Edited_date_and_time": "2019-07-16T20:00:00.000-05:00",
    "_status": "submitted_via_web",
    "formhub/uuid": "bf9676788f314c00a984ea8002333ac1",
    "username": "username not found",
    "_validation_status": {},
    "_uuid": "eb6d25d3-2255-4288-83a0-271c9a2760f9",
    "_submitted_by": null,
    "group_ve9cv03/Site_name": "Cana",
    "What_did_you_find": "site",
    "__version__": "vJLQEGi5dLMUNuBsjGNRmu",
    "Edited_by": "1503628_CAL",
    "_submission_time": "2021-03-29T23:16:18",
    "_attachments": [],
    "deviceid": "ee.kobotoolbox.org:SamGhFwda0v8M1oh",
    "_id": 90565636,
    "Record_your_current_location": "7.90420277777777 -77.6426388888889 0 0"
  },
  {
    "_notes": [],
    "_tags": [],
    "_xform_id_string": "apHdoBqmXMLQkiok6Pdjea",
    "meta/instanceID": "uuid:22d30b58-0496-4022-be2c-53d410ae957b",
    "Recorded_by": "1503628_CAL",
    "end": "2021-03-29T19:23:07.088-05:00",
    "Enter_date_and_time_of_discovery": "2019-07-16T15:08:00.000-05:00",
    "start": "2021-03-29T19:18:33.807-05:00",
    "_geolocation": [
      null,
      null
    ],
    "Edited_date_and_time": "2019-07-16T15:08:00.000-05:00",
    "_status": "submitted_via_web",
    "formhub/uuid": "bf9676788f314c00a984ea8002333ac1",
    "username": "username not found",
    "_validation_status": {},
    "_uuid": "22d30b58-0496-4022-be2c-53d410ae957b",
    "_submitted_by": null,
    "group_vm75p90/Description_005": "Chert nodules",
    "What_did_you_find": "chipped_stone",
    "__version__": "vJLQEGi5dLMUNuBsjGNRmu",
    "Edited_by": "1503628_CAL",
    "_submission_time": "2021-03-30T00:24:37",
    "_attachments": [{
      "mimetype": "image/jpeg",
      "download_small_url": "https://kc.kobotoolbox.org/media/small?media_file=dariengap2021%2Fattachments%2Fbf9676788f314c00a984ea8002333ac1%2F22d30b58-0496-4022-be2c-53d410ae957b%2F24-12_1_56-19_22_47.jpg",
      "download_large_url": "https://kc.kobotoolbox.org/media/large?media_file=dariengap2021%2Fattachments%2Fbf9676788f314c00a984ea8002333ac1%2F22d30b58-0496-4022-be2c-53d410ae957b%2F24-12_1_56-19_22_47.jpg",
      "download_url": "https://kc.kobotoolbox.org/media/original?media_file=dariengap2021%2Fattachments%2Fbf9676788f314c00a984ea8002333ac1%2F22d30b58-0496-4022-be2c-53d410ae957b%2F24-12_1_56-19_22_47.jpg",
      "filename": "dariengap2021/attachments/bf9676788f314c00a984ea8002333ac1/22d30b58-0496-4022-be2c-53d410ae957b/24-12_1_56-19_22_47.jpg",
      "instance": 90568654,
      "download_medium_url": "https://kc.kobotoolbox.org/media/medium?media_file=dariengap2021%2Fattachments%2Fbf9676788f314c00a984ea8002333ac1%2F22d30b58-0496-4022-be2c-53d410ae957b%2F24-12_1_56-19_22_47.jpg",
      "id": 32009318,
      "xform": 639284
    }],
    "deviceid": "ee.kobotoolbox.org:SamGhFwda0v8M1oh",
    "_id": 90568654,
    "group_qk9bw75": [{
      "group_qk9bw75/Photo_1": "24-12_1_56-19_22_47.jpg"
    }]
  },
  {
    "_notes": [],
    "_xform_id_string": "apHdoBqmXMLQkiok6Pdjea",
    "_tags": [],
    "group_ve9cv03/Current_use": "other__otro",
    "meta/instanceID": "uuid:4aa36945-2687-4ae3-9a04-291b25bb3769",
    "group_ve9cv03/Current_vegetation": "trees__rboles",
    "Recorded_by": "1503628_CAL",
    "group_ve9cv03/Parallel_visibility": "medium",
    "Enter_date_and_time_of_discovery": "2019-07-01T01:34:00.000-05:00",
    "group_ve9cv03/Local_soil_name": "no hay",
    "group_ve9cv03/Non_human_disturbance": "vegetaci_n",
    "group_ve9cv03/Conservation": "very_disturbed",
    "start": "2021-03-29T19:41:18.214-05:00",
    "group_ve9cv03/Surface_soil": "_arena",
    "_attachments": [{
      "mimetype": "image/jpeg",
      "download_small_url": "https://kc.kobotoolbox.org/media/small?media_file=dariengap2021%2Fattachments%2Fbf9676788f314c00a984ea8002333ac1%2F4aa36945-2687-4ae3-9a04-291b25bb3769%2F11-15_32_22-19_52_46.jpg",
      "download_large_url": "https://kc.kobotoolbox.org/media/large?media_file=dariengap2021%2Fattachments%2Fbf9676788f314c00a984ea8002333ac1%2F4aa36945-2687-4ae3-9a04-291b25bb3769%2F11-15_32_22-19_52_46.jpg",
      "download_url": "https://kc.kobotoolbox.org/media/original?media_file=dariengap2021%2Fattachments%2Fbf9676788f314c00a984ea8002333ac1%2F4aa36945-2687-4ae3-9a04-291b25bb3769%2F11-15_32_22-19_52_46.jpg",
      "filename": "dariengap2021/attachments/bf9676788f314c00a984ea8002333ac1/4aa36945-2687-4ae3-9a04-291b25bb3769/11-15_32_22-19_52_46.jpg",
      "instance": 90569634,
      "download_medium_url": "https://kc.kobotoolbox.org/media/medium?media_file=dariengap2021%2Fattachments%2Fbf9676788f314c00a984ea8002333ac1%2F4aa36945-2687-4ae3-9a04-291b25bb3769%2F11-15_32_22-19_52_46.jpg",
      "id": 32009782,
      "xform": 639284
    }],
    "Edited_date_and_time": "2019-07-16T15:08:00.000-05:00",
    "_status": "submitted_via_web",
    "formhub/uuid": "bf9676788f314c00a984ea8002333ac1",
    "username": "username not found",
    "_validation_status": {},
    "_uuid": "4aa36945-2687-4ae3-9a04-291b25bb3769",
    "Record_your_current_location": "8.065823 -78.361782 0 0",
    "_submitted_by": null,
    "group_dy8ma60/Description_003": "Oldest parts of the site = south and southwest. Mound area is newer (more pirangua). Immediately on the other side of the river there was ceramic -- possibly different people or time period but possibly related. Silty sand. Mound is 1.5m ish tall and 5 m long. Contemporary occupants of Garachine continue to dump waste here -- but many different species also that previously were not seen (in contemporary areas around houses, for example). Site covers an area of roughly 25m x 35m.",
    "end": "2021-03-29T19:53:00.530-05:00",
    "What_did_you_find": "site mound",
    "group_ve9cv03/Landowner": "Don Antonio",
    "__version__": "vJLQEGi5dLMUNuBsjGNRmu",
    "Edited_by": "1503628_CAL",
    "group_ve9cv03/Ground_visibility": "medium",
    "_submission_time": "2021-03-30T00:54:25",
    "group_ve9cv03/Description_001": "site type-disposal area",
    "_geolocation": [
      8.065823,
      -78.361782
    ],
    "group_dy8ma60/Site_name_002": "Piangual",
    "deviceid": "ee.kobotoolbox.org:SamGhFwda0v8M1oh",
    "group_ve9cv03/Anthropological_disturbance": "other__otro",
    "_id": 90569634,
    "group_qk9bw75": [{
      "group_qk9bw75/Photo_1": "11-15_32_22-19_52_46.jpg"
    }]
  },
  {
    "_notes": [],
    "_tags": [],
    "_xform_id_string": "apHdoBqmXMLQkiok6Pdjea",
    "meta/instanceID": "uuid:33363376-4b70-4e0a-8b0d-d6a11f88f737",
    "Recorded_by": "1503628_CAL",
    "end": "2021-03-29T19:41:18.121-05:00",
    "Enter_date_and_time_of_discovery": "2019-07-16T15:08:00.000-05:00",
    "start": "2021-03-29T19:38:30.641-05:00",
    "_geolocation": [
      8.275938,
      -78.151443
    ],
    "Edited_date_and_time": "2019-07-16T15:08:00.000-05:00",
    "_status": "submitted_via_web",
    "formhub/uuid": "bf9676788f314c00a984ea8002333ac1",
    "username": "username not found",
    "_validation_status": {},
    "_uuid": "33363376-4b70-4e0a-8b0d-d6a11f88f737",
    "_submitted_by": null,
    "group_qk9bw75": [{
      "group_qk9bw75/Photo_1": "7-11_57_14-19_40_58.jpg"
    }],
    "What_did_you_find": "ceramic",
    "__version__": "vJLQEGi5dLMUNuBsjGNRmu",
    "Edited_by": "1503628_CAL",
    "_submission_time": "2021-03-30T00:42:42",
    "_attachments": [{
      "mimetype": "image/jpeg",
      "download_small_url": "https://kc.kobotoolbox.org/media/small?media_file=dariengap2021%2Fattachments%2Fbf9676788f314c00a984ea8002333ac1%2F33363376-4b70-4e0a-8b0d-d6a11f88f737%2F7-11_57_14-19_40_58.jpg",
      "download_large_url": "https://kc.kobotoolbox.org/media/large?media_file=dariengap2021%2Fattachments%2Fbf9676788f314c00a984ea8002333ac1%2F33363376-4b70-4e0a-8b0d-d6a11f88f737%2F7-11_57_14-19_40_58.jpg",
      "download_url": "https://kc.kobotoolbox.org/media/original?media_file=dariengap2021%2Fattachments%2Fbf9676788f314c00a984ea8002333ac1%2F33363376-4b70-4e0a-8b0d-d6a11f88f737%2F7-11_57_14-19_40_58.jpg",
      "filename": "dariengap2021/attachments/bf9676788f314c00a984ea8002333ac1/33363376-4b70-4e0a-8b0d-d6a11f88f737/7-11_57_14-19_40_58.jpg",
      "instance": 90569123,
      "download_medium_url": "https://kc.kobotoolbox.org/media/medium?media_file=dariengap2021%2Fattachments%2Fbf9676788f314c00a984ea8002333ac1%2F33363376-4b70-4e0a-8b0d-d6a11f88f737%2F7-11_57_14-19_40_58.jpg",
      "id": 32009690,
      "xform": 639284
    }],
    "deviceid": "ee.kobotoolbox.org:SamGhFwda0v8M1oh",
    "_id": 90569123,
    "Record_your_current_location": "8.275938 -78.151443 0 0"
  },
  {
    "_notes": [],
    "group_ve9cv03/Site_type": "agricultural__agr_cola",
    "group_sj61b88/Description_009": "Soil underneath = reddish brown but soil above = brownish black (tierra negra, seems like barrial -- cracks when it is dry). Wider from 4th terrace on. 16 terraces, heights are variable. soil is way more reddish at the top. some are disturbed from modern human and cow trampling. Irregular top -- terrace before coming down again. NW side slopes down gradually but only 4 steps. Really terraced part (SE) discharges into stream (where you get the most water). First samples taken from between terraces 6 and 7 (horizontal tubes T7 and T8). Terrace 7 width =80cm, terrace 6 width =60cm, depth between them =140cm.",
    "_xform_id_string": "apHdoBqmXMLQkiok6Pdjea",
    "_tags": [],
    "group_ve9cv03/Current_use": "pasture__pasto",
    "meta/instanceID": "uuid:41e7add4-38d7-41c8-a4b1-175a173deff4",
    "group_ve9cv03/Current_vegetation": "grassland__pastizales",
    "Recorded_by": "Lucy Gill",
    "group_ve9cv03/Parallel_visibility": "high",
    "Enter_date_and_time_of_discovery": "2019-07-16T19:15:00.000-05:00",
    "group_ve9cv03/Local_soil_name": "no se",
    "group_ve9cv03/Non_human_disturbance": "pisoteo_de_animales",
    "group_ve9cv03/Conservation": "moderately_disturbed",
    "start": "2021-03-29T19:10:29.759-05:00",
    "group_ve9cv03/Surface_soil": "_limo",
    "_attachments": [{
      "mimetype": "image/jpeg",
      "download_small_url": "https://kc.kobotoolbox.org/media/small?media_file=dariengap2021%2Fattachments%2Fbf9676788f314c00a984ea8002333ac1%2Feeaa831c-752d-48b6-bbe8-269718676fa8%2F15-11_44_48-19_18_25.jpg",
      "download_large_url": "https://kc.kobotoolbox.org/media/large?media_file=dariengap2021%2Fattachments%2Fbf9676788f314c00a984ea8002333ac1%2Feeaa831c-752d-48b6-bbe8-269718676fa8%2F15-11_44_48-19_18_25.jpg",
      "download_url": "https://kc.kobotoolbox.org/media/original?media_file=dariengap2021%2Fattachments%2Fbf9676788f314c00a984ea8002333ac1%2Feeaa831c-752d-48b6-bbe8-269718676fa8%2F15-11_44_48-19_18_25.jpg",
      "filename": "dariengap2021/attachments/bf9676788f314c00a984ea8002333ac1/eeaa831c-752d-48b6-bbe8-269718676fa8/15-11_44_48-19_18_25.jpg",
      "instance": 90568498,
      "download_medium_url": "https://kc.kobotoolbox.org/media/medium?media_file=dariengap2021%2Fattachments%2Fbf9676788f314c00a984ea8002333ac1%2Feeaa831c-752d-48b6-bbe8-269718676fa8%2F15-11_44_48-19_18_25.jpg",
      "id": 32009182,
      "xform": 639284
    }],
    "Edited_date_and_time": "2019-07-16T15:08:00.000-05:00",
    "_status": "submitted_via_web",
    "formhub/uuid": "bf9676788f314c00a984ea8002333ac1",
    "meta/deprecatedID": "uuid:eeaa831c-752d-48b6-bbe8-269718676fa8",
    "username": "username not found",
    "_validation_status": {},
    "_uuid": "41e7add4-38d7-41c8-a4b1-175a173deff4",
    "Record_your_current_location": "8.310707 -78.122819 0 0",
    "_submitted_by": null,
    "end": "2021-03-29T20:50:18.295-05:00",
    "group_ve9cv03/Site_name": "Terrazza",
    "What_did_you_find": "site other",
    "__version__": "vJLQEGi5dLMUNuBsjGNRmu",
    "Edited_by": "1503628_CAL",
    "group_ve9cv03/Ground_visibility": "low",
    "group_ve9cv03/group_qn6ym49": [{
      "group_ve9cv03/group_qn6ym49/Other_items_present_or_absent": "mound pathway terrace"
    }],
    "_submission_time": "2021-03-30T00:20:00",
    "_geolocation": [
      8.310707,
      -78.122819
    ],
    "deviceid": "ee.kobotoolbox.org:SamGhFwda0v8M1oh",
    "group_ve9cv03/Anthropological_disturbance": "_agricultura",
    "_id": 90568498,
    "group_qk9bw75": [{
      "group_qk9bw75/Photo_1": "15-11_44_48-19_18_25.jpg"
    }]
  },
  {
    "_notes": [],
    "_tags": [],
    "_xform_id_string": "apHdoBqmXMLQkiok6Pdjea",
    "_geolocation": [
      8.287543,
      -78.27808
    ],
    "Recorded_by": "1503628_CAL",
    "end": "2021-03-29T18:40:19.555-05:00",
    "Enter_date_and_time_of_discovery": "2019-07-16T15:08:00.000-05:00",
    "start": "2021-03-29T18:36:10.180-05:00",
    "Edited_date_and_time": "2019-07-16T15:08:00.000-05:00",
    "_status": "submitted_via_web",
    "formhub/uuid": "bf9676788f314c00a984ea8002333ac1",
    "username": "username not found",
    "meta/instanceID": "uuid:b28c722d-9c45-4cfb-876b-b0ce7f4f5bb8",
    "_validation_status": {},
    "_uuid": "b28c722d-9c45-4cfb-876b-b0ce7f4f5bb8",
    "_submitted_by": null,
    "group_ve9cv03/Site_name": "Punta Barro Colorado",
    "group_qk9bw75": [{
      "group_qk9bw75/Photo_1": "object29-20_6_4-18_39_52.jpg"
    }],
    "What_did_you_find": "site other",
    "__version__": "vJLQEGi5dLMUNuBsjGNRmu",
    "Edited_by": "1503628_CAL",
    "_submission_time": "2021-03-29T23:41:52",
    "_attachments": [{
      "mimetype": "image/jpeg",
      "download_small_url": "https://kc.kobotoolbox.org/media/small?media_file=dariengap2021%2Fattachments%2Fbf9676788f314c00a984ea8002333ac1%2Fb28c722d-9c45-4cfb-876b-b0ce7f4f5bb8%2Fobject29-20_6_4-18_39_52.jpg",
      "download_large_url": "https://kc.kobotoolbox.org/media/large?media_file=dariengap2021%2Fattachments%2Fbf9676788f314c00a984ea8002333ac1%2Fb28c722d-9c45-4cfb-876b-b0ce7f4f5bb8%2Fobject29-20_6_4-18_39_52.jpg",
      "download_url": "https://kc.kobotoolbox.org/media/original?media_file=dariengap2021%2Fattachments%2Fbf9676788f314c00a984ea8002333ac1%2Fb28c722d-9c45-4cfb-876b-b0ce7f4f5bb8%2Fobject29-20_6_4-18_39_52.jpg",
      "filename": "dariengap2021/attachments/bf9676788f314c00a984ea8002333ac1/b28c722d-9c45-4cfb-876b-b0ce7f4f5bb8/object29-20_6_4-18_39_52.jpg",
      "instance": 90567040,
      "download_medium_url": "https://kc.kobotoolbox.org/media/medium?media_file=dariengap2021%2Fattachments%2Fbf9676788f314c00a984ea8002333ac1%2Fb28c722d-9c45-4cfb-876b-b0ce7f4f5bb8%2Fobject29-20_6_4-18_39_52.jpg",
      "id": 32008345,
      "xform": 639284
    }],
    "deviceid": "ee.kobotoolbox.org:SamGhFwda0v8M1oh",
    "_id": 90567040,
    "Record_your_current_location": "8.287543 -78.27808 0 0"
  },
  {
    "_notes": [],
    "group_ap6sf60/Rock_Type": "other",
    "group_ap6sf60/Bedrock_outcrop": "yes",
    "_tags": [],
    "_xform_id_string": "apHdoBqmXMLQkiok6Pdjea",
    "meta/instanceID": "uuid:73c30b45-caae-497d-8476-a3b34e04a120",
    "Recorded_by": "Lucy Gill",
    "end": "2021-03-29T20:48:12.140-05:00",
    "Enter_date_and_time_of_discovery": "2019-06-30T13:20:00.000-05:00",
    "start": "2021-03-29T18:48:41.307-05:00",
    "_attachments": [{
      "mimetype": "image/jpeg",
      "download_small_url": "https://kc.kobotoolbox.org/media/small?media_file=dariengap2021%2Fattachments%2Fbf9676788f314c00a984ea8002333ac1%2Fc6ba6756-ada7-45af-aad9-52b7c4d23cc1%2Fobject1-10_51_35-18_59_29.jpg",
      "download_large_url": "https://kc.kobotoolbox.org/media/large?media_file=dariengap2021%2Fattachments%2Fbf9676788f314c00a984ea8002333ac1%2Fc6ba6756-ada7-45af-aad9-52b7c4d23cc1%2Fobject1-10_51_35-18_59_29.jpg",
      "download_url": "https://kc.kobotoolbox.org/media/original?media_file=dariengap2021%2Fattachments%2Fbf9676788f314c00a984ea8002333ac1%2Fc6ba6756-ada7-45af-aad9-52b7c4d23cc1%2Fobject1-10_51_35-18_59_29.jpg",
      "filename": "dariengap2021/attachments/bf9676788f314c00a984ea8002333ac1/c6ba6756-ada7-45af-aad9-52b7c4d23cc1/object1-10_51_35-18_59_29.jpg",
      "instance": 90567682,
      "download_medium_url": "https://kc.kobotoolbox.org/media/medium?media_file=dariengap2021%2Fattachments%2Fbf9676788f314c00a984ea8002333ac1%2Fc6ba6756-ada7-45af-aad9-52b7c4d23cc1%2Fobject1-10_51_35-18_59_29.jpg",
      "id": 32008661,
      "xform": 639284
    }],
    "Edited_date_and_time": "2019-07-16T15:08:00.000-05:00",
    "group_ap6sf60/Maximum_height": "300",
    "_status": "submitted_via_web",
    "formhub/uuid": "bf9676788f314c00a984ea8002333ac1",
    "meta/deprecatedID": "uuid:c6ba6756-ada7-45af-aad9-52b7c4d23cc1",
    "username": "username not found",
    "_validation_status": {},
    "_uuid": "73c30b45-caae-497d-8476-a3b34e04a120",
    "group_ap6sf60/Non_human_disturbance_001": "vegetaci_n",
    "group_ap6sf60/Mound_Association": "none",
    "group_ap6sf60/Site_name_001": "La Mola",
    "_submitted_by": null,
    "group_ap6sf60/Conservation_001": "moderately_disturbed",
    "group_ap6sf60/Length": "300",
    "group_ap6sf60/Width": "200",
    "__version__": "vJLQEGi5dLMUNuBsjGNRmu",
    "What_did_you_find": "site petroglyph",
    "group_ap6sf60/Anthropological_disturbance_001": "other__otro",
    "Edited_by": "1503628_CAL",
    "_submission_time": "2021-03-30T00:03:13",
    "_geolocation": [
      8.232602,
      -78.164041
    ],
    "deviceid": "ee.kobotoolbox.org:SamGhFwda0v8M1oh",
    "Record_your_current_location": "8.232602 -78.164041 0 0",
    "_id": 90567682,
    "group_qk9bw75": [{
      "group_qk9bw75/Photo_1": "object1-10_51_35-18_59_29.jpg"
    }]
  },
  {
    "_notes": [],
    "_tags": [],
    "_xform_id_string": "apHdoBqmXMLQkiok6Pdjea",
    "meta/instanceID": "uuid:4dc0d0f9-d17e-4d43-91ac-e6a8fdf454f1",
    "Recorded_by": "1503628_CAL",
    "end": "2021-03-29T19:34:51.603-05:00",
    "Enter_date_and_time_of_discovery": "2019-07-16T15:08:00.000-05:00",
    "start": "2021-03-29T19:31:15.482-05:00",
    "_geolocation": [
      8.258018,
      -78.309208
    ],
    "Edited_date_and_time": "2019-07-16T15:08:00.000-05:00",
    "_status": "submitted_via_web",
    "formhub/uuid": "bf9676788f314c00a984ea8002333ac1",
    "username": "username not found",
    "_validation_status": {},
    "_uuid": "4dc0d0f9-d17e-4d43-91ac-e6a8fdf454f1",
    "_submitted_by": null,
    "group_qk9bw75": [{
      "group_qk9bw75/Photo_1": "31-10_44_52-19_34_39.jpg"
    }],
    "What_did_you_find": "mound",
    "__version__": "vJLQEGi5dLMUNuBsjGNRmu",
    "Edited_by": "1503628_CAL",
    "_submission_time": "2021-03-30T00:36:16",
    "_attachments": [{
      "mimetype": "image/jpeg",
      "download_small_url": "https://kc.kobotoolbox.org/media/small?media_file=dariengap2021%2Fattachments%2Fbf9676788f314c00a984ea8002333ac1%2F4dc0d0f9-d17e-4d43-91ac-e6a8fdf454f1%2F31-10_44_52-19_34_39.jpg",
      "download_large_url": "https://kc.kobotoolbox.org/media/large?media_file=dariengap2021%2Fattachments%2Fbf9676788f314c00a984ea8002333ac1%2F4dc0d0f9-d17e-4d43-91ac-e6a8fdf454f1%2F31-10_44_52-19_34_39.jpg",
      "download_url": "https://kc.kobotoolbox.org/media/original?media_file=dariengap2021%2Fattachments%2Fbf9676788f314c00a984ea8002333ac1%2F4dc0d0f9-d17e-4d43-91ac-e6a8fdf454f1%2F31-10_44_52-19_34_39.jpg",
      "filename": "dariengap2021/attachments/bf9676788f314c00a984ea8002333ac1/4dc0d0f9-d17e-4d43-91ac-e6a8fdf454f1/31-10_44_52-19_34_39.jpg",
      "instance": 90568973,
      "download_medium_url": "https://kc.kobotoolbox.org/media/medium?media_file=dariengap2021%2Fattachments%2Fbf9676788f314c00a984ea8002333ac1%2F4dc0d0f9-d17e-4d43-91ac-e6a8fdf454f1%2F31-10_44_52-19_34_39.jpg",
      "id": 32009607,
      "xform": 639284
    }],
    "group_dy8ma60/Site_name_002": "Morro Pati침o (isla)",
    "deviceid": "ee.kobotoolbox.org:SamGhFwda0v8M1oh",
    "_id": 90568973,
    "Record_your_current_location": "8.258018 -78.309208 0 0"
  },
  {
    "_notes": [],
    "_tags": [],
    "_xform_id_string": "apHdoBqmXMLQkiok6Pdjea",
    "meta/instanceID": "uuid:c1b6752c-34c8-4e61-b7d5-9e44e0193d68",
    "Recorded_by": "1503628_CAL",
    "end": "2021-03-29T19:26:49.129-05:00",
    "Enter_date_and_time_of_discovery": "2019-07-16T15:08:00.000-05:00",
    "start": "2021-03-29T19:23:07.178-05:00",
    "_geolocation": [
      8.276,
      -78.151516
    ],
    "Edited_date_and_time": "2019-07-16T15:08:00.000-05:00",
    "_status": "submitted_via_web",
    "formhub/uuid": "bf9676788f314c00a984ea8002333ac1",
    "username": "username not found",
    "_validation_status": {},
    "_uuid": "c1b6752c-34c8-4e61-b7d5-9e44e0193d68",
    "_submitted_by": null,
    "group_qk9bw75": [{
      "group_qk9bw75/Photo_1": "8-11_59_31-19_26_12.jpg"
    }],
    "What_did_you_find": "ceramic",
    "__version__": "vJLQEGi5dLMUNuBsjGNRmu",
    "Edited_by": "1503628_CAL",
    "_submission_time": "2021-03-30T00:28:21",
    "_attachments": [{
      "mimetype": "image/jpeg",
      "download_small_url": "https://kc.kobotoolbox.org/media/small?media_file=dariengap2021%2Fattachments%2Fbf9676788f314c00a984ea8002333ac1%2Fc1b6752c-34c8-4e61-b7d5-9e44e0193d68%2F8-11_59_31-19_26_12.jpg",
      "download_large_url": "https://kc.kobotoolbox.org/media/large?media_file=dariengap2021%2Fattachments%2Fbf9676788f314c00a984ea8002333ac1%2Fc1b6752c-34c8-4e61-b7d5-9e44e0193d68%2F8-11_59_31-19_26_12.jpg",
      "download_url": "https://kc.kobotoolbox.org/media/original?media_file=dariengap2021%2Fattachments%2Fbf9676788f314c00a984ea8002333ac1%2Fc1b6752c-34c8-4e61-b7d5-9e44e0193d68%2F8-11_59_31-19_26_12.jpg",
      "filename": "dariengap2021/attachments/bf9676788f314c00a984ea8002333ac1/c1b6752c-34c8-4e61-b7d5-9e44e0193d68/8-11_59_31-19_26_12.jpg",
      "instance": 90568737,
      "download_medium_url": "https://kc.kobotoolbox.org/media/medium?media_file=dariengap2021%2Fattachments%2Fbf9676788f314c00a984ea8002333ac1%2Fc1b6752c-34c8-4e61-b7d5-9e44e0193d68%2F8-11_59_31-19_26_12.jpg",
      "id": 32009423,
      "xform": 639284
    }],
    "deviceid": "ee.kobotoolbox.org:SamGhFwda0v8M1oh",
    "group_ni8nm64/Description_006": "Probably recent. Para recoger agua.",
    "_id": 90568737,
    "Record_your_current_location": "8.276 -78.151516 0 0"
  },
  {
    "_notes": [],
    "group_sj61b88/Description_009": "Ca침on",
    "_tags": [],
    "_xform_id_string": "apHdoBqmXMLQkiok6Pdjea",
    "meta/instanceID": "uuid:4c3912e4-cf56-4871-aac3-c42d6f427f2d",
    "Recorded_by": "1503628_CAL",
    "end": "2021-03-29T19:31:15.393-05:00",
    "Enter_date_and_time_of_discovery": "2019-07-16T15:08:00.000-05:00",
    "start": "2021-03-29T19:26:49.243-05:00",
    "_geolocation": [
      8.11111,
      -77.735518
    ],
    "Edited_date_and_time": "2019-07-16T15:08:00.000-05:00",
    "_status": "submitted_via_web",
    "formhub/uuid": "bf9676788f314c00a984ea8002333ac1",
    "username": "username not found",
    "_validation_status": {},
    "_uuid": "4c3912e4-cf56-4871-aac3-c42d6f427f2d",
    "_submitted_by": null,
    "group_qk9bw75": [{
      "group_qk9bw75/Photo_1": "37-11_31_23-19_30_47.jpg"
    }],
    "What_did_you_find": "other",
    "__version__": "vJLQEGi5dLMUNuBsjGNRmu",
    "Edited_by": "1503628_CAL",
    "_submission_time": "2021-03-30T00:32:40",
    "_attachments": [{
      "mimetype": "image/jpeg",
      "download_small_url": "https://kc.kobotoolbox.org/media/small?media_file=dariengap2021%2Fattachments%2Fbf9676788f314c00a984ea8002333ac1%2F4c3912e4-cf56-4871-aac3-c42d6f427f2d%2F37-11_31_23-19_30_47.jpg",
      "download_large_url": "https://kc.kobotoolbox.org/media/large?media_file=dariengap2021%2Fattachments%2Fbf9676788f314c00a984ea8002333ac1%2F4c3912e4-cf56-4871-aac3-c42d6f427f2d%2F37-11_31_23-19_30_47.jpg",
      "download_url": "https://kc.kobotoolbox.org/media/original?media_file=dariengap2021%2Fattachments%2Fbf9676788f314c00a984ea8002333ac1%2F4c3912e4-cf56-4871-aac3-c42d6f427f2d%2F37-11_31_23-19_30_47.jpg",
      "filename": "dariengap2021/attachments/bf9676788f314c00a984ea8002333ac1/4c3912e4-cf56-4871-aac3-c42d6f427f2d/37-11_31_23-19_30_47.jpg",
      "instance": 90568853,
      "download_medium_url": "https://kc.kobotoolbox.org/media/medium?media_file=dariengap2021%2Fattachments%2Fbf9676788f314c00a984ea8002333ac1%2F4c3912e4-cf56-4871-aac3-c42d6f427f2d%2F37-11_31_23-19_30_47.jpg",
      "id": 32009475,
      "xform": 639284
    }],
    "deviceid": "ee.kobotoolbox.org:SamGhFwda0v8M1oh",
    "_id": 90568853,
    "Record_your_current_location": "8.11111 -77.735518 0 0"
  },
  {
    "_notes": [],
    "_tags": [],
    "_xform_id_string": "apHdoBqmXMLQkiok6Pdjea",
    "meta/instanceID": "uuid:f284a0dd-94b7-428b-a18a-3dfa55168fc7",
    "Recorded_by": "Linne 1929",
    "end": "2021-03-29T18:09:49.715-05:00",
    "Enter_date_and_time_of_discovery": "2019-07-16T15:07:00.000-05:00",
    "start": "2021-03-29T17:58:58.899-05:00",
    "_geolocation": [
      8.439809,
      -78.26555556
    ],
    "Edited_date_and_time": "2019-07-16T15:07:00.000-05:00",
    "_status": "submitted_via_web",
    "formhub/uuid": "bf9676788f314c00a984ea8002333ac1",
    "username": "username not found",
    "_validation_status": {},
    "_uuid": "f284a0dd-94b7-428b-a18a-3dfa55168fc7",
    "_submitted_by": null,
    "group_ve9cv03/Site_name": "RioSanMiguel",
    "What_did_you_find": "site",
    "__version__": "vJLQEGi5dLMUNuBsjGNRmu",
    "Edited_by": "1503628_CAL",
    "_submission_time": "2021-03-29T23:11:12",
    "group_ve9cv03/Description_001": "At a place 1 to 1 1/2 kilometre distant from the river's mouth, a natural selection of one of its banks has formed from the erosive action of the river. The river flows nearly due north to south, and archaeological deposits were found on its west bank, over an area extending to a length of about 75 m. In the north end of the old dwelling site, at a height of about 1 m above water at ebb-tide, and more or less awash at flood-tide, there is a stratum, almost of the character of cement, containing shells (of uniform type) admixed with a low proportion of pottery fragments. Farther up on the river above this site no traces of ancient habitation were found, but towards its mouth discovered pottery fragments, although sparingly, in the present river bed.",
    "_attachments": [],
    "deviceid": "ee.kobotoolbox.org:SamGhFwda0v8M1oh",
    "_id": 90565381,
    "Record_your_current_location": "8.439809 -78.26555556 0 0"
  },
  {
    "_notes": [],
    "_tags": [],
    "_xform_id_string": "apHdoBqmXMLQkiok6Pdjea",
    "meta/instanceID": "uuid:d5c69335-910b-4046-8e86-defcf6d9be34",
    "Recorded_by": "1503628_CAL",
    "end": "2021-03-29T18:36:10.085-05:00",
    "Enter_date_and_time_of_discovery": "2019-07-16T15:08:00.000-05:00",
    "group_ni8nm64/Incisions": "absent",
    "start": "2021-03-29T18:14:56.743-05:00",
    "group_ni8nm64/Polychromes": "present",
    "_attachments": [{
      "mimetype": "image/jpeg",
      "download_small_url": "https://kc.kobotoolbox.org/media/small?media_file=dariengap2021%2Fattachments%2Fbf9676788f314c00a984ea8002333ac1%2Fd5c69335-910b-4046-8e86-defcf6d9be34%2Fobject4-20_4_14-18_34_48.jpg",
      "download_large_url": "https://kc.kobotoolbox.org/media/large?media_file=dariengap2021%2Fattachments%2Fbf9676788f314c00a984ea8002333ac1%2Fd5c69335-910b-4046-8e86-defcf6d9be34%2Fobject4-20_4_14-18_34_48.jpg",
      "download_url": "https://kc.kobotoolbox.org/media/original?media_file=dariengap2021%2Fattachments%2Fbf9676788f314c00a984ea8002333ac1%2Fd5c69335-910b-4046-8e86-defcf6d9be34%2Fobject4-20_4_14-18_34_48.jpg",
      "filename": "dariengap2021/attachments/bf9676788f314c00a984ea8002333ac1/d5c69335-910b-4046-8e86-defcf6d9be34/object4-20_4_14-18_34_48.jpg",
      "instance": 90566948,
      "download_medium_url": "https://kc.kobotoolbox.org/media/medium?media_file=dariengap2021%2Fattachments%2Fbf9676788f314c00a984ea8002333ac1%2Fd5c69335-910b-4046-8e86-defcf6d9be34%2Fobject4-20_4_14-18_34_48.jpg",
      "id": 32008276,
      "xform": 639284
    }],
    "Edited_date_and_time": "2019-07-16T15:08:00.000-05:00",
    "_status": "submitted_via_web",
    "formhub/uuid": "bf9676788f314c00a984ea8002333ac1",
    "username": "username not found",
    "_validation_status": {},
    "_uuid": "d5c69335-910b-4046-8e86-defcf6d9be34",
    "_submitted_by": null,
    "What_did_you_find": "ceramic",
    "__version__": "vJLQEGi5dLMUNuBsjGNRmu",
    "Edited_by": "1503628_CAL",
    "_submission_time": "2021-03-29T23:37:38",
    "_geolocation": [
      8.284148,
      -78.043596
    ],
    "deviceid": "ee.kobotoolbox.org:SamGhFwda0v8M1oh",
    "Record_your_current_location": "8.284148 -78.043596 0 0",
    "_id": 90566948,
    "group_qk9bw75": [{
      "group_qk9bw75/Photo_1": "object4-20_4_14-18_34_48.jpg"
    }]
  },
  {
    "_notes": [],
    "_tags": [],
    "_xform_id_string": "apHdoBqmXMLQkiok6Pdjea",
    "meta/instanceID": "uuid:bab1b4e5-4fd2-413b-9067-3b2b9e67bbd6",
    "Recorded_by": "1503628_CAL",
    "end": "2021-03-29T19:38:30.501-05:00",
    "Enter_date_and_time_of_discovery": "2019-07-16T15:08:00.000-05:00",
    "start": "2021-03-29T19:34:51.676-05:00",
    "_geolocation": [
      8.27577,
      -78.151028
    ],
    "Edited_date_and_time": "2019-07-16T15:08:00.000-05:00",
    "_status": "submitted_via_web",
    "formhub/uuid": "bf9676788f314c00a984ea8002333ac1",
    "username": "username not found",
    "_validation_status": {},
    "_uuid": "bab1b4e5-4fd2-413b-9067-3b2b9e67bbd6",
    "_submitted_by": null,
    "group_qk9bw75": [{
      "group_qk9bw75/Photo_1": "6-11_56_46-19_38_20.jpg"
    }],
    "What_did_you_find": "flora",
    "__version__": "vJLQEGi5dLMUNuBsjGNRmu",
    "Edited_by": "1503628_CAL",
    "_submission_time": "2021-03-30T00:39:57",
    "_attachments": [{
      "mimetype": "image/jpeg",
      "download_small_url": "https://kc.kobotoolbox.org/media/small?media_file=dariengap2021%2Fattachments%2Fbf9676788f314c00a984ea8002333ac1%2Fbab1b4e5-4fd2-413b-9067-3b2b9e67bbd6%2F6-11_56_46-19_38_20.jpg",
      "download_large_url": "https://kc.kobotoolbox.org/media/large?media_file=dariengap2021%2Fattachments%2Fbf9676788f314c00a984ea8002333ac1%2Fbab1b4e5-4fd2-413b-9067-3b2b9e67bbd6%2F6-11_56_46-19_38_20.jpg",
      "download_url": "https://kc.kobotoolbox.org/media/original?media_file=dariengap2021%2Fattachments%2Fbf9676788f314c00a984ea8002333ac1%2Fbab1b4e5-4fd2-413b-9067-3b2b9e67bbd6%2F6-11_56_46-19_38_20.jpg",
      "filename": "dariengap2021/attachments/bf9676788f314c00a984ea8002333ac1/bab1b4e5-4fd2-413b-9067-3b2b9e67bbd6/6-11_56_46-19_38_20.jpg",
      "instance": 90569057,
      "download_medium_url": "https://kc.kobotoolbox.org/media/medium?media_file=dariengap2021%2Fattachments%2Fbf9676788f314c00a984ea8002333ac1%2Fbab1b4e5-4fd2-413b-9067-3b2b9e67bbd6%2F6-11_56_46-19_38_20.jpg",
      "id": 32009660,
      "xform": 639284
    }],
    "deviceid": "ee.kobotoolbox.org:SamGhFwda0v8M1oh",
    "_id": 90569057,
    "Record_your_current_location": "8.27577 -78.151028 0 0"
  },
  {
    "_notes": [],
    "group_ve9cv03/Site_type": "mortuary__mortuorio",
    "_tags": [],
    "_xform_id_string": "apHdoBqmXMLQkiok6Pdjea",
    "meta/instanceID": "uuid:cb3868b7-264f-4adf-8693-ae8d0dfb9e7b",
    "Recorded_by": "Lucy Gill",
    "end": "2021-03-29T18:48:41.219-05:00",
    "Enter_date_and_time_of_discovery": "2019-07-02T09:05:00.000-05:00",
    "group_ve9cv03/Local_soil_name": "no hay",
    "group_ve9cv03/Non_human_disturbance": "vegetaci_n",
    "group_ve9cv03/Conservation": "very_disturbed",
    "start": "2021-03-29T18:40:19.645-05:00",
    "group_ve9cv03/Surface_soil": "_limo _arcilla",
    "_attachments": [{
      "mimetype": "image/jpeg",
      "download_small_url": "https://kc.kobotoolbox.org/media/small?media_file=dariengap2021%2Fattachments%2Fbf9676788f314c00a984ea8002333ac1%2Fcb3868b7-264f-4adf-8693-ae8d0dfb9e7b%2Fobject14-10_35_57-18_48_33.jpg",
      "download_large_url": "https://kc.kobotoolbox.org/media/large?media_file=dariengap2021%2Fattachments%2Fbf9676788f314c00a984ea8002333ac1%2Fcb3868b7-264f-4adf-8693-ae8d0dfb9e7b%2Fobject14-10_35_57-18_48_33.jpg",
      "download_url": "https://kc.kobotoolbox.org/media/original?media_file=dariengap2021%2Fattachments%2Fbf9676788f314c00a984ea8002333ac1%2Fcb3868b7-264f-4adf-8693-ae8d0dfb9e7b%2Fobject14-10_35_57-18_48_33.jpg",
      "filename": "dariengap2021/attachments/bf9676788f314c00a984ea8002333ac1/cb3868b7-264f-4adf-8693-ae8d0dfb9e7b/object14-10_35_57-18_48_33.jpg",
      "instance": 90567227,
      "download_medium_url": "https://kc.kobotoolbox.org/media/medium?media_file=dariengap2021%2Fattachments%2Fbf9676788f314c00a984ea8002333ac1%2Fcb3868b7-264f-4adf-8693-ae8d0dfb9e7b%2Fobject14-10_35_57-18_48_33.jpg",
      "id": 32008496,
      "xform": 639284
    }],
    "Edited_date_and_time": "2019-07-16T15:08:00.000-05:00",
    "_status": "submitted_via_web",
    "formhub/uuid": "bf9676788f314c00a984ea8002333ac1",
    "username": "username not found",
    "_validation_status": {},
    "_uuid": "cb3868b7-264f-4adf-8693-ae8d0dfb9e7b",
    "Record_your_current_location": "8.061104 -78.358803 0 0",
    "_submitted_by": null,
    "group_ve9cv03/Site_name": "SanAntonio",
    "What_did_you_find": "site",
    "group_ve9cv03/Landowner": "Virgilio Bayastero",
    "__version__": "vJLQEGi5dLMUNuBsjGNRmu",
    "Edited_by": "Lucy Gill",
    "group_ve9cv03/Ground_visibility": "high",
    "group_ve9cv03/group_qn6ym49": [{
      "group_ve9cv03/group_qn6ym49/Other_items_present_or_absent": "ceramic groundstone obsidian mortar mound pathway loose_stones"
    }],
    "_submission_time": "2021-03-29T23:50:15",
    "_geolocation": [
      8.061104,
      -78.358803
    ],
    "deviceid": "ee.kobotoolbox.org:SamGhFwda0v8M1oh",
    "group_ve9cv03/Anthropological_disturbance": "other__otro",
    "_id": 90567227,
    "group_qk9bw75": [{
      "group_qk9bw75/Photo_1": "object14-10_35_57-18_48_33.jpg"
    }]
  },
  {
    "_notes": [],
    "group_sj61b88/Description_009": "Quebrada Ca침치 only that does not dry out except Quebrada Lucas",
    "_tags": [],
    "_xform_id_string": "apHdoBqmXMLQkiok6Pdjea",
    "meta/instanceID": "uuid:5cdeeed0-a5ff-44ac-a604-275e0a060603",
    "Recorded_by": "1503628_CAL",
    "end": "2021-03-29T19:10:29.662-05:00",
    "Enter_date_and_time_of_discovery": "2019-07-16T15:08:00.000-05:00",
    "start": "2021-03-29T19:06:23.049-05:00",
    "_geolocation": [
      8.275967,
      -78.1514
    ],
    "Edited_date_and_time": "2019-07-16T15:08:00.000-05:00",
    "_status": "submitted_via_web",
    "formhub/uuid": "bf9676788f314c00a984ea8002333ac1",
    "username": "username not found",
    "_validation_status": {},
    "_uuid": "5cdeeed0-a5ff-44ac-a604-275e0a060603",
    "_submitted_by": null,
    "group_qk9bw75": [{
      "group_qk9bw75/Photo_1": "23-11_43_17-19_10_11.jpg"
    }],
    "What_did_you_find": "other",
    "__version__": "vJLQEGi5dLMUNuBsjGNRmu",
    "Edited_by": "1503628_CAL",
    "_submission_time": "2021-03-30T00:12:12",
    "_attachments": [{
      "mimetype": "image/jpeg",
      "download_small_url": "https://kc.kobotoolbox.org/media/small?media_file=dariengap2021%2Fattachments%2Fbf9676788f314c00a984ea8002333ac1%2F5cdeeed0-a5ff-44ac-a604-275e0a060603%2F23-11_43_17-19_10_11.jpg",
      "download_large_url": "https://kc.kobotoolbox.org/media/large?media_file=dariengap2021%2Fattachments%2Fbf9676788f314c00a984ea8002333ac1%2F5cdeeed0-a5ff-44ac-a604-275e0a060603%2F23-11_43_17-19_10_11.jpg",
      "download_url": "https://kc.kobotoolbox.org/media/original?media_file=dariengap2021%2Fattachments%2Fbf9676788f314c00a984ea8002333ac1%2F5cdeeed0-a5ff-44ac-a604-275e0a060603%2F23-11_43_17-19_10_11.jpg",
      "filename": "dariengap2021/attachments/bf9676788f314c00a984ea8002333ac1/5cdeeed0-a5ff-44ac-a604-275e0a060603/23-11_43_17-19_10_11.jpg",
      "instance": 90567991,
      "download_medium_url": "https://kc.kobotoolbox.org/media/medium?media_file=dariengap2021%2Fattachments%2Fbf9676788f314c00a984ea8002333ac1%2F5cdeeed0-a5ff-44ac-a604-275e0a060603%2F23-11_43_17-19_10_11.jpg",
      "id": 32008881,
      "xform": 639284
    }],
    "deviceid": "ee.kobotoolbox.org:SamGhFwda0v8M1oh",
    "_id": 90567991,
    "Record_your_current_location": "8.275967 -78.1514 0 0"
  },
  {
    "_notes": [],
    "_tags": [],
    "_xform_id_string": "apHdoBqmXMLQkiok6Pdjea",
    "meta/instanceID": "uuid:043749de-5359-46d2-8ab5-d0dcc0ca051d",
    "Recorded_by": "Piperno 1994",
    "end": "2021-03-29T19:05:23.917-05:00",
    "Enter_date_and_time_of_discovery": "2019-07-16T15:07:00.000-05:00",
    "start": "2021-03-29T19:01:43.030-05:00",
    "_geolocation": [
      7.90420277777777,
      -77.6426388888889
    ],
    "Edited_date_and_time": "2019-07-16T15:07:00.000-05:00",
    "_status": "submitted_via_web",
    "formhub/uuid": "bf9676788f314c00a984ea8002333ac1",
    "username": "username not found",
    "_validation_status": {},
    "_uuid": "043749de-5359-46d2-8ab5-d0dcc0ca051d",
    "_submitted_by": null,
    "group_ve9cv03/Site_name": "Cana",
    "What_did_you_find": "site",
    "__version__": "vJLQEGi5dLMUNuBsjGNRmu",
    "Edited_by": "Piperno 1994",
    "_submission_time": "2021-03-30T00:06:47",
    "_attachments": [],
    "deviceid": "ee.kobotoolbox.org:SamGhFwda0v8M1oh",
    "_id": 90567797,
    "Record_your_current_location": "7.90420277777777 -77.6426388888889 0 0"
  },
  {
    "_notes": [],
    "_tags": [],
    "_xform_id_string": "apHdoBqmXMLQkiok6Pdjea",
    "meta/instanceID": "uuid:fa9155d5-850d-4d81-94cc-4f53e3d41058",
    "Recorded_by": "1503628_CAL",
    "end": "2021-03-29T20:28:40.872-05:00",
    "Enter_date_and_time_of_discovery": "2019-07-16T15:08:00.000-05:00",
    "start": "2021-03-29T20:25:38.555-05:00",
    "_geolocation": [
      8.365992,
      -77.89621
    ],
    "Edited_date_and_time": "2019-07-16T15:08:00.000-05:00",
    "_status": "submitted_via_web",
    "formhub/uuid": "bf9676788f314c00a984ea8002333ac1",
    "username": "username not found",
    "_validation_status": {},
    "_uuid": "fa9155d5-850d-4d81-94cc-4f53e3d41058",
    "_submitted_by": null,
    "group_bl1nk04/Description_007": "plantas de behuco, solamente aqui. y un pedazo de pedernal",
    "group_qk9bw75": [{
      "group_qk9bw75/Photo_1": "11_Lucy-16_23_50-20_28_30.jpg"
    }],
    "What_did_you_find": "flora",
    "__version__": "vJLQEGi5dLMUNuBsjGNRmu",
    "Edited_by": "1503628_CAL",
    "_submission_time": "2021-03-30T01:30:05",
    "_attachments": [{
      "mimetype": "image/jpeg",
      "download_small_url": "https://kc.kobotoolbox.org/media/small?media_file=dariengap2021%2Fattachments%2Fbf9676788f314c00a984ea8002333ac1%2Ffa9155d5-850d-4d81-94cc-4f53e3d41058%2F11_Lucy-16_23_50-20_28_30.jpg",
      "download_large_url": "https://kc.kobotoolbox.org/media/large?media_file=dariengap2021%2Fattachments%2Fbf9676788f314c00a984ea8002333ac1%2Ffa9155d5-850d-4d81-94cc-4f53e3d41058%2F11_Lucy-16_23_50-20_28_30.jpg",
      "download_url": "https://kc.kobotoolbox.org/media/original?media_file=dariengap2021%2Fattachments%2Fbf9676788f314c00a984ea8002333ac1%2Ffa9155d5-850d-4d81-94cc-4f53e3d41058%2F11_Lucy-16_23_50-20_28_30.jpg",
      "filename": "dariengap2021/attachments/bf9676788f314c00a984ea8002333ac1/fa9155d5-850d-4d81-94cc-4f53e3d41058/11_Lucy-16_23_50-20_28_30.jpg",
      "instance": 90570957,
      "download_medium_url": "https://kc.kobotoolbox.org/media/medium?media_file=dariengap2021%2Fattachments%2Fbf9676788f314c00a984ea8002333ac1%2Ffa9155d5-850d-4d81-94cc-4f53e3d41058%2F11_Lucy-16_23_50-20_28_30.jpg",
      "id": 32010620,
      "xform": 639284
    }],
    "deviceid": "ee.kobotoolbox.org:SamGhFwda0v8M1oh",
    "_id": 90570957,
    "Record_your_current_location": "8.365992 -77.89621 0 0"
  },
  {
    "_notes": [],
    "group_sj61b88/Description_009": "Clay sample from quebrada for cows.",
    "_tags": [],
    "_xform_id_string": "apHdoBqmXMLQkiok6Pdjea",
    "meta/instanceID": "uuid:ad7b6c07-72ea-440b-86e5-9761134b13a6",
    "Recorded_by": "1503628_CAL",
    "end": "2021-03-29T20:40:17.704-05:00",
    "Enter_date_and_time_of_discovery": "2019-07-16T15:08:00.000-05:00",
    "start": "2021-03-29T20:37:29.352-05:00",
    "_geolocation": [
      8.061107,
      -78.359888
    ],
    "Edited_date_and_time": "2019-07-16T15:08:00.000-05:00",
    "_status": "submitted_via_web",
    "formhub/uuid": "bf9676788f314c00a984ea8002333ac1",
    "username": "username not found",
    "_validation_status": {},
    "_uuid": "ad7b6c07-72ea-440b-86e5-9761134b13a6",
    "_submitted_by": null,
    "group_qk9bw75": [{
      "group_qk9bw75/Photo_1": "34-16_47_54-20_40_0.jpg"
    }],
    "What_did_you_find": "other",
    "__version__": "vJLQEGi5dLMUNuBsjGNRmu",
    "Edited_by": "1503628_CAL",
    "_submission_time": "2021-03-30T01:41:42",
    "_attachments": [{
      "mimetype": "image/jpeg",
      "download_small_url": "https://kc.kobotoolbox.org/media/small?media_file=dariengap2021%2Fattachments%2Fbf9676788f314c00a984ea8002333ac1%2Fad7b6c07-72ea-440b-86e5-9761134b13a6%2F34-16_47_54-20_40_0.jpg",
      "download_large_url": "https://kc.kobotoolbox.org/media/large?media_file=dariengap2021%2Fattachments%2Fbf9676788f314c00a984ea8002333ac1%2Fad7b6c07-72ea-440b-86e5-9761134b13a6%2F34-16_47_54-20_40_0.jpg",
      "download_url": "https://kc.kobotoolbox.org/media/original?media_file=dariengap2021%2Fattachments%2Fbf9676788f314c00a984ea8002333ac1%2Fad7b6c07-72ea-440b-86e5-9761134b13a6%2F34-16_47_54-20_40_0.jpg",
      "filename": "dariengap2021/attachments/bf9676788f314c00a984ea8002333ac1/ad7b6c07-72ea-440b-86e5-9761134b13a6/34-16_47_54-20_40_0.jpg",
      "instance": 90571230,
      "download_medium_url": "https://kc.kobotoolbox.org/media/medium?media_file=dariengap2021%2Fattachments%2Fbf9676788f314c00a984ea8002333ac1%2Fad7b6c07-72ea-440b-86e5-9761134b13a6%2F34-16_47_54-20_40_0.jpg",
      "id": 32010771,
      "xform": 639284
    }],
    "deviceid": "ee.kobotoolbox.org:SamGhFwda0v8M1oh",
    "_id": 90571230,
    "Record_your_current_location": "8.061107 -78.359888 0 0"
  },
  {
    "_notes": [],
    "group_sj61b88/Description_009": "rock, 'hammer'/Martillo. In a shell midden -- but shells seem modern.",
    "_tags": [],
    "_xform_id_string": "apHdoBqmXMLQkiok6Pdjea",
    "meta/instanceID": "uuid:bd1a2b46-c20d-451c-872b-591633016c34",
    "Recorded_by": "1503628_CAL",
    "end": "2021-03-29T20:05:50.644-05:00",
    "Enter_date_and_time_of_discovery": "2019-07-16T15:08:00.000-05:00",
    "start": "2021-03-29T20:01:26.656-05:00",
    "_geolocation": [
      8.061132,
      -78.363737
    ],
    "Edited_date_and_time": "2019-07-16T15:08:00.000-05:00",
    "_status": "submitted_via_web",
    "formhub/uuid": "bf9676788f314c00a984ea8002333ac1",
    "username": "username not found",
    "_validation_status": {},
    "_uuid": "bd1a2b46-c20d-451c-872b-591633016c34",
    "_submitted_by": null,
    "group_qk9bw75": [{
      "group_qk9bw75/Photo_1": "5-15_51_9-20_5_36.jpg"
    }],
    "What_did_you_find": "other",
    "__version__": "vJLQEGi5dLMUNuBsjGNRmu",
    "Edited_by": "1503628_CAL",
    "_submission_time": "2021-03-30T01:07:15",
    "_attachments": [{
      "mimetype": "image/jpeg",
      "download_small_url": "https://kc.kobotoolbox.org/media/small?media_file=dariengap2021%2Fattachments%2Fbf9676788f314c00a984ea8002333ac1%2Fbd1a2b46-c20d-451c-872b-591633016c34%2F5-15_51_9-20_5_36.jpg",
      "download_large_url": "https://kc.kobotoolbox.org/media/large?media_file=dariengap2021%2Fattachments%2Fbf9676788f314c00a984ea8002333ac1%2Fbd1a2b46-c20d-451c-872b-591633016c34%2F5-15_51_9-20_5_36.jpg",
      "download_url": "https://kc.kobotoolbox.org/media/original?media_file=dariengap2021%2Fattachments%2Fbf9676788f314c00a984ea8002333ac1%2Fbd1a2b46-c20d-451c-872b-591633016c34%2F5-15_51_9-20_5_36.jpg",
      "filename": "dariengap2021/attachments/bf9676788f314c00a984ea8002333ac1/bd1a2b46-c20d-451c-872b-591633016c34/5-15_51_9-20_5_36.jpg",
      "instance": 90569996,
      "download_medium_url": "https://kc.kobotoolbox.org/media/medium?media_file=dariengap2021%2Fattachments%2Fbf9676788f314c00a984ea8002333ac1%2Fbd1a2b46-c20d-451c-872b-591633016c34%2F5-15_51_9-20_5_36.jpg",
      "id": 32009989,
      "xform": 639284
    }],
    "deviceid": "ee.kobotoolbox.org:SamGhFwda0v8M1oh",
    "_id": 90569996,
    "Record_your_current_location": "8.061132 -78.363737 0 0"
  },
  {
    "_notes": [],
    "_tags": [],
    "_xform_id_string": "apHdoBqmXMLQkiok6Pdjea",
    "meta/instanceID": "uuid:86119ca2-b2c5-4b9d-afc2-b7eeb154739b",
    "group_du78m73/Description_004": "Sandstone concentration, same rock used for groundstone artifacts from Casa Calderon.",
    "Recorded_by": "1503628_CAL",
    "end": "2021-03-29T20:37:29.237-05:00",
    "Enter_date_and_time_of_discovery": "2019-07-16T15:08:00.000-05:00",
    "start": "2021-03-29T20:34:50.572-05:00",
    "_geolocation": [
      8.367118,
      -77.89805
    ],
    "Edited_date_and_time": "2019-07-16T15:08:00.000-05:00",
    "_status": "submitted_via_web",
    "formhub/uuid": "bf9676788f314c00a984ea8002333ac1",
    "username": "username not found",
    "_validation_status": {},
    "_uuid": "86119ca2-b2c5-4b9d-afc2-b7eeb154739b",
    "_submitted_by": null,
    "group_qk9bw75": [{
      "group_qk9bw75/Photo_1": "8_Lucy-16_37_44-20_37_22.jpg"
    }],
    "What_did_you_find": "groundstone",
    "__version__": "vJLQEGi5dLMUNuBsjGNRmu",
    "Edited_by": "1503628_CAL",
    "_submission_time": "2021-03-30T01:38:53",
    "_attachments": [{
      "mimetype": "image/jpeg",
      "download_small_url": "https://kc.kobotoolbox.org/media/small?media_file=dariengap2021%2Fattachments%2Fbf9676788f314c00a984ea8002333ac1%2F86119ca2-b2c5-4b9d-afc2-b7eeb154739b%2F8_Lucy-16_37_44-20_37_22.jpg",
      "download_large_url": "https://kc.kobotoolbox.org/media/large?media_file=dariengap2021%2Fattachments%2Fbf9676788f314c00a984ea8002333ac1%2F86119ca2-b2c5-4b9d-afc2-b7eeb154739b%2F8_Lucy-16_37_44-20_37_22.jpg",
      "download_url": "https://kc.kobotoolbox.org/media/original?media_file=dariengap2021%2Fattachments%2Fbf9676788f314c00a984ea8002333ac1%2F86119ca2-b2c5-4b9d-afc2-b7eeb154739b%2F8_Lucy-16_37_44-20_37_22.jpg",
      "filename": "dariengap2021/attachments/bf9676788f314c00a984ea8002333ac1/86119ca2-b2c5-4b9d-afc2-b7eeb154739b/8_Lucy-16_37_44-20_37_22.jpg",
      "instance": 90571145,
      "download_medium_url": "https://kc.kobotoolbox.org/media/medium?media_file=dariengap2021%2Fattachments%2Fbf9676788f314c00a984ea8002333ac1%2F86119ca2-b2c5-4b9d-afc2-b7eeb154739b%2F8_Lucy-16_37_44-20_37_22.jpg",
      "id": 32010708,
      "xform": 639284
    }],
    "deviceid": "ee.kobotoolbox.org:SamGhFwda0v8M1oh",
    "_id": 90571145,
    "Record_your_current_location": "8.367118 -77.89805 0 0"
  },
  {
    "_notes": [],
    "_tags": [],
    "_xform_id_string": "apHdoBqmXMLQkiok6Pdjea",
    "meta/instanceID": "uuid:9e30d069-45fb-478f-b22a-d29cfa863a3a",
    "group_du78m73/Description_004": "Bonanza Arcilla Roja. NRD took sample for reference collection. Need to take out the small stones before it is usable.",
    "Recorded_by": "1503628_CAL",
    "end": "2021-03-29T20:34:50.470-05:00",
    "Enter_date_and_time_of_discovery": "2019-07-16T15:08:00.000-05:00",
    "start": "2021-03-29T20:31:47.127-05:00",
    "_geolocation": [
      8.364883,
      -77.895165
    ],
    "Edited_date_and_time": "2019-07-16T15:08:00.000-05:00",
    "_status": "submitted_via_web",
    "formhub/uuid": "bf9676788f314c00a984ea8002333ac1",
    "username": "username not found",
    "_validation_status": {},
    "_uuid": "9e30d069-45fb-478f-b22a-d29cfa863a3a",
    "_submitted_by": null,
    "group_qk9bw75": [{
      "group_qk9bw75/Photo_1": "12-16_31_55-20_34_39.jpg"
    }],
    "What_did_you_find": "groundstone",
    "__version__": "vJLQEGi5dLMUNuBsjGNRmu",
    "Edited_by": "1503628_CAL",
    "_submission_time": "2021-03-30T01:36:14",
    "_attachments": [{
      "mimetype": "image/jpeg",
      "download_small_url": "https://kc.kobotoolbox.org/media/small?media_file=dariengap2021%2Fattachments%2Fbf9676788f314c00a984ea8002333ac1%2F9e30d069-45fb-478f-b22a-d29cfa863a3a%2F12-16_31_55-20_34_39.jpg",
      "download_large_url": "https://kc.kobotoolbox.org/media/large?media_file=dariengap2021%2Fattachments%2Fbf9676788f314c00a984ea8002333ac1%2F9e30d069-45fb-478f-b22a-d29cfa863a3a%2F12-16_31_55-20_34_39.jpg",
      "download_url": "https://kc.kobotoolbox.org/media/original?media_file=dariengap2021%2Fattachments%2Fbf9676788f314c00a984ea8002333ac1%2F9e30d069-45fb-478f-b22a-d29cfa863a3a%2F12-16_31_55-20_34_39.jpg",
      "filename": "dariengap2021/attachments/bf9676788f314c00a984ea8002333ac1/9e30d069-45fb-478f-b22a-d29cfa863a3a/12-16_31_55-20_34_39.jpg",
      "instance": 90571075,
      "download_medium_url": "https://kc.kobotoolbox.org/media/medium?media_file=dariengap2021%2Fattachments%2Fbf9676788f314c00a984ea8002333ac1%2F9e30d069-45fb-478f-b22a-d29cfa863a3a%2F12-16_31_55-20_34_39.jpg",
      "id": 32010673,
      "xform": 639284
    }],
    "deviceid": "ee.kobotoolbox.org:SamGhFwda0v8M1oh",
    "_id": 90571075,
    "Record_your_current_location": "8.364883 -77.895165 0 0"
  },
  {
    "_notes": [],
    "_tags": [],
    "_xform_id_string": "apHdoBqmXMLQkiok6Pdjea",
    "meta/instanceID": "uuid:0f8f87bc-9518-47bd-82ab-9f01695e42d7",
    "group_du78m73/Description_004": "Typology: metate",
    "Recorded_by": "1503628_CAL",
    "end": "2021-03-29T20:31:46.999-05:00",
    "Enter_date_and_time_of_discovery": "2019-07-16T15:08:00.000-05:00",
    "start": "2021-03-29T20:28:40.978-05:00",
    "_attachments": [{
      "mimetype": "image/jpeg",
      "download_small_url": "https://kc.kobotoolbox.org/media/small?media_file=dariengap2021%2Fattachments%2Fbf9676788f314c00a984ea8002333ac1%2F0f8f87bc-9518-47bd-82ab-9f01695e42d7%2F2-16_28_26-20_31_20.jpg",
      "download_large_url": "https://kc.kobotoolbox.org/media/large?media_file=dariengap2021%2Fattachments%2Fbf9676788f314c00a984ea8002333ac1%2F0f8f87bc-9518-47bd-82ab-9f01695e42d7%2F2-16_28_26-20_31_20.jpg",
      "download_url": "https://kc.kobotoolbox.org/media/original?media_file=dariengap2021%2Fattachments%2Fbf9676788f314c00a984ea8002333ac1%2F0f8f87bc-9518-47bd-82ab-9f01695e42d7%2F2-16_28_26-20_31_20.jpg",
      "filename": "dariengap2021/attachments/bf9676788f314c00a984ea8002333ac1/0f8f87bc-9518-47bd-82ab-9f01695e42d7/2-16_28_26-20_31_20.jpg",
      "instance": 90571019,
      "download_medium_url": "https://kc.kobotoolbox.org/media/medium?media_file=dariengap2021%2Fattachments%2Fbf9676788f314c00a984ea8002333ac1%2F0f8f87bc-9518-47bd-82ab-9f01695e42d7%2F2-16_28_26-20_31_20.jpg",
      "id": 32010639,
      "xform": 639284
    }],
    "Edited_date_and_time": "2019-07-16T15:08:00.000-05:00",
    "_status": "submitted_via_web",
    "formhub/uuid": "bf9676788f314c00a984ea8002333ac1",
    "username": "username not found",
    "_validation_status": {},
    "_uuid": "0f8f87bc-9518-47bd-82ab-9f01695e42d7",
    "_submitted_by": null,
    "What_did_you_find": "groundstone",
    "__version__": "vJLQEGi5dLMUNuBsjGNRmu",
    "Edited_by": "1503628_CAL",
    "group_du78m73/Rock_type_002": "Sandstone",
    "_submission_time": "2021-03-30T01:33:10",
    "_geolocation": [
      8.366768,
      -77.896915
    ],
    "deviceid": "ee.kobotoolbox.org:SamGhFwda0v8M1oh",
    "Record_your_current_location": "8.366768 -77.896915 0 0",
    "_id": 90571019,
    "group_qk9bw75": [{
      "group_qk9bw75/Photo_1": "2-16_28_26-20_31_20.jpg"
    }]
  },
  {
    "_notes": [],
    "group_ve9cv03/Site_type": "housing__habitacional",
    "_xform_id_string": "apHdoBqmXMLQkiok6Pdjea",
    "_tags": [],
    "group_ve9cv03/Current_use": "agriculture__agricultura",
    "meta/instanceID": "uuid:50453649-e9cb-442b-8d0c-db38a361a402",
    "group_ve9cv03/Current_vegetation": "trees__rboles",
    "Recorded_by": "Lucy Gill",
    "group_ve9cv03/Parallel_visibility": "low",
    "Enter_date_and_time_of_discovery": "2019-07-16T15:08:00.000-05:00",
    "group_ve9cv03/Non_human_disturbance": "otro",
    "group_ve9cv03/Conservation": "moderately_disturbed",
    "start": "2021-03-29T20:21:19.580-05:00",
    "group_ve9cv03/Surface_soil": "_limo",
    "_attachments": [{
      "mimetype": "image/jpeg",
      "download_small_url": "https://kc.kobotoolbox.org/media/small?media_file=dariengap2021%2Fattachments%2Fbf9676788f314c00a984ea8002333ac1%2F50453649-e9cb-442b-8d0c-db38a361a402%2F5_Lucy-16_20_17-20_25_29.jpg",
      "download_large_url": "https://kc.kobotoolbox.org/media/large?media_file=dariengap2021%2Fattachments%2Fbf9676788f314c00a984ea8002333ac1%2F50453649-e9cb-442b-8d0c-db38a361a402%2F5_Lucy-16_20_17-20_25_29.jpg",
      "download_url": "https://kc.kobotoolbox.org/media/original?media_file=dariengap2021%2Fattachments%2Fbf9676788f314c00a984ea8002333ac1%2F50453649-e9cb-442b-8d0c-db38a361a402%2F5_Lucy-16_20_17-20_25_29.jpg",
      "filename": "dariengap2021/attachments/bf9676788f314c00a984ea8002333ac1/50453649-e9cb-442b-8d0c-db38a361a402/5_Lucy-16_20_17-20_25_29.jpg",
      "instance": 90570876,
      "download_medium_url": "https://kc.kobotoolbox.org/media/medium?media_file=dariengap2021%2Fattachments%2Fbf9676788f314c00a984ea8002333ac1%2F50453649-e9cb-442b-8d0c-db38a361a402%2F5_Lucy-16_20_17-20_25_29.jpg",
      "id": 32010591,
      "xform": 639284
    }],
    "Edited_date_and_time": "2019-07-16T15:08:00.000-05:00",
    "_status": "submitted_via_web",
    "formhub/uuid": "bf9676788f314c00a984ea8002333ac1",
    "username": "username not found",
    "_validation_status": {},
    "_uuid": "50453649-e9cb-442b-8d0c-db38a361a402",
    "Record_your_current_location": "8.361565 -77.898918 0 0",
    "_submitted_by": null,
    "end": "2021-03-29T20:25:38.438-05:00",
    "group_ve9cv03/Site_name": "Finca El Lago",
    "What_did_you_find": "site",
    "__version__": "vJLQEGi5dLMUNuBsjGNRmu",
    "Edited_by": "1503628_CAL",
    "group_ve9cv03/Ground_visibility": "medium",
    "group_ve9cv03/group_qn6ym49": [{
      "group_ve9cv03/group_qn6ym49/Other_items_present_or_absent": "ceramic pathway"
    }],
    "_submission_time": "2021-03-30T01:27:01",
    "group_ve9cv03/Description_001": "Found ceramics around the house, other things have been collected as well",
    "_geolocation": [
      8.361565,
      -77.898918
    ],
    "deviceid": "ee.kobotoolbox.org:SamGhFwda0v8M1oh",
    "group_ve9cv03/Anthropological_disturbance": "_agricultura",
    "_id": 90570876,
    "group_qk9bw75": [{
      "group_qk9bw75/Photo_1": "5_Lucy-16_20_17-20_25_29.jpg"
    }]
  },
  {
    "_notes": [],
    "group_sj61b88/Description_009": "tierra firme",
    "_tags": [],
    "_xform_id_string": "apHdoBqmXMLQkiok6Pdjea",
    "meta/instanceID": "uuid:6a50b551-e0fd-4012-8394-33ccc8377438",
    "Recorded_by": "1503628_CAL",
    "end": "2021-03-29T20:21:19.471-05:00",
    "Enter_date_and_time_of_discovery": "2019-07-16T15:08:00.000-05:00",
    "start": "2021-03-29T20:17:18.388-05:00",
    "_geolocation": [
      -78.181473,
      -78.181473
    ],
    "Edited_date_and_time": "2019-07-16T15:08:00.000-05:00",
    "_status": "submitted_via_web",
    "formhub/uuid": "bf9676788f314c00a984ea8002333ac1",
    "username": "username not found",
    "_validation_status": {},
    "_uuid": "6a50b551-e0fd-4012-8394-33ccc8377438",
    "_submitted_by": null,
    "group_qk9bw75": [{
      "group_qk9bw75/Photo_1": "28-16_11_9-20_21_10.jpg"
    }],
    "What_did_you_find": "other",
    "__version__": "vJLQEGi5dLMUNuBsjGNRmu",
    "Edited_by": "1503628_CAL",
    "_submission_time": "2021-03-30T01:22:46",
    "_attachments": [{
      "mimetype": "image/jpeg",
      "download_small_url": "https://kc.kobotoolbox.org/media/small?media_file=dariengap2021%2Fattachments%2Fbf9676788f314c00a984ea8002333ac1%2F6a50b551-e0fd-4012-8394-33ccc8377438%2F28-16_11_9-20_21_10.jpg",
      "download_large_url": "https://kc.kobotoolbox.org/media/large?media_file=dariengap2021%2Fattachments%2Fbf9676788f314c00a984ea8002333ac1%2F6a50b551-e0fd-4012-8394-33ccc8377438%2F28-16_11_9-20_21_10.jpg",
      "download_url": "https://kc.kobotoolbox.org/media/original?media_file=dariengap2021%2Fattachments%2Fbf9676788f314c00a984ea8002333ac1%2F6a50b551-e0fd-4012-8394-33ccc8377438%2F28-16_11_9-20_21_10.jpg",
      "filename": "dariengap2021/attachments/bf9676788f314c00a984ea8002333ac1/6a50b551-e0fd-4012-8394-33ccc8377438/28-16_11_9-20_21_10.jpg",
      "instance": 90570706,
      "download_medium_url": "https://kc.kobotoolbox.org/media/medium?media_file=dariengap2021%2Fattachments%2Fbf9676788f314c00a984ea8002333ac1%2F6a50b551-e0fd-4012-8394-33ccc8377438%2F28-16_11_9-20_21_10.jpg",
      "id": 32010461,
      "xform": 639284
    }],
    "deviceid": "ee.kobotoolbox.org:SamGhFwda0v8M1oh",
    "_id": 90570706,
    "Record_your_current_location": "-78.181473 -78.181473 0 0"
  },
  {
    "_notes": [],
    "_tags": [],
    "_xform_id_string": "apHdoBqmXMLQkiok6Pdjea",
    "_geolocation": [
      8.119214,
      -77.78982
    ],
    "Recorded_by": "1503628_CAL",
    "end": "2021-03-29T20:10:51.628-05:00",
    "Enter_date_and_time_of_discovery": "2019-07-16T15:08:00.000-05:00",
    "start": "2021-03-29T20:05:50.734-05:00",
    "Edited_date_and_time": "2019-07-16T15:08:00.000-05:00",
    "_status": "submitted_via_web",
    "formhub/uuid": "bf9676788f314c00a984ea8002333ac1",
    "username": "username not found",
    "meta/instanceID": "uuid:9201ecc9-2af1-4591-ad32-2df9674988b7",
    "_validation_status": {},
    "_uuid": "9201ecc9-2af1-4591-ad32-2df9674988b7",
    "_submitted_by": null,
    "group_ve9cv03/Site_name": "point of disembarcation Tuira 1",
    "group_qk9bw75": [{
      "group_qk9bw75/Photo_1": "39-15_59_39-20_10_42.jpg"
    }],
    "What_did_you_find": "site",
    "__version__": "vJLQEGi5dLMUNuBsjGNRmu",
    "Edited_by": "1503628_CAL",
    "_submission_time": "2021-03-30T01:12:15",
    "_attachments": [{
      "mimetype": "image/jpeg",
      "download_small_url": "https://kc.kobotoolbox.org/media/small?media_file=dariengap2021%2Fattachments%2Fbf9676788f314c00a984ea8002333ac1%2F9201ecc9-2af1-4591-ad32-2df9674988b7%2F39-15_59_39-20_10_42.jpg",
      "download_large_url": "https://kc.kobotoolbox.org/media/large?media_file=dariengap2021%2Fattachments%2Fbf9676788f314c00a984ea8002333ac1%2F9201ecc9-2af1-4591-ad32-2df9674988b7%2F39-15_59_39-20_10_42.jpg",
      "download_url": "https://kc.kobotoolbox.org/media/original?media_file=dariengap2021%2Fattachments%2Fbf9676788f314c00a984ea8002333ac1%2F9201ecc9-2af1-4591-ad32-2df9674988b7%2F39-15_59_39-20_10_42.jpg",
      "filename": "dariengap2021/attachments/bf9676788f314c00a984ea8002333ac1/9201ecc9-2af1-4591-ad32-2df9674988b7/39-15_59_39-20_10_42.jpg",
      "instance": 90570148,
      "download_medium_url": "https://kc.kobotoolbox.org/media/medium?media_file=dariengap2021%2Fattachments%2Fbf9676788f314c00a984ea8002333ac1%2F9201ecc9-2af1-4591-ad32-2df9674988b7%2F39-15_59_39-20_10_42.jpg",
      "id": 32010113,
      "xform": 639284
    }],
    "deviceid": "ee.kobotoolbox.org:SamGhFwda0v8M1oh",
    "_id": 90570148,
    "Record_your_current_location": "8.119214 -77.78982 0 0"
  },
  {
    "_notes": [],
    "_xform_id_string": "apHdoBqmXMLQkiok6Pdjea",
    "_tags": [],
    "group_ve9cv03/Current_use": "other__otro",
    "meta/instanceID": "uuid:5d24ca84-2a35-4076-9b31-f34c5feb7c0a",
    "Recorded_by": "Lucy Gill",
    "group_ve9cv03/Parallel_visibility": "high",
    "Enter_date_and_time_of_discovery": "2019-06-24T16:45:00.000-05:00",
    "group_ve9cv03/Non_human_disturbance": "erosi_n",
    "group_ve9cv03/Conservation": "intact",
    "start": "2021-03-29T20:10:51.730-05:00",
    "group_ve9cv03/Surface_soil": "_limo",
    "_attachments": [{
        "mimetype": "image/jpeg",
        "download_small_url": "https://kc.kobotoolbox.org/media/small?media_file=dariengap2021%2Fattachments%2Fbf9676788f314c00a984ea8002333ac1%2F5d24ca84-2a35-4076-9b31-f34c5feb7c0a%2F3b-16_2_40-20_17_7.jpg",
        "download_large_url": "https://kc.kobotoolbox.org/media/large?media_file=dariengap2021%2Fattachments%2Fbf9676788f314c00a984ea8002333ac1%2F5d24ca84-2a35-4076-9b31-f34c5feb7c0a%2F3b-16_2_40-20_17_7.jpg",
        "download_url": "https://kc.kobotoolbox.org/media/original?media_file=dariengap2021%2Fattachments%2Fbf9676788f314c00a984ea8002333ac1%2F5d24ca84-2a35-4076-9b31-f34c5feb7c0a%2F3b-16_2_40-20_17_7.jpg",
        "filename": "dariengap2021/attachments/bf9676788f314c00a984ea8002333ac1/5d24ca84-2a35-4076-9b31-f34c5feb7c0a/3b-16_2_40-20_17_7.jpg",
        "instance": 90570460,
        "download_medium_url": "https://kc.kobotoolbox.org/media/medium?media_file=dariengap2021%2Fattachments%2Fbf9676788f314c00a984ea8002333ac1%2F5d24ca84-2a35-4076-9b31-f34c5feb7c0a%2F3b-16_2_40-20_17_7.jpg",
        "id": 32010346,
        "xform": 639284
      },
      {
        "mimetype": "image/jpeg",
        "download_small_url": "https://kc.kobotoolbox.org/media/small?media_file=dariengap2021%2Fattachments%2Fbf9676788f314c00a984ea8002333ac1%2F5d24ca84-2a35-4076-9b31-f34c5feb7c0a%2F3a-16_2_36-20_16_34.jpg",
        "download_large_url": "https://kc.kobotoolbox.org/media/large?media_file=dariengap2021%2Fattachments%2Fbf9676788f314c00a984ea8002333ac1%2F5d24ca84-2a35-4076-9b31-f34c5feb7c0a%2F3a-16_2_36-20_16_34.jpg",
        "download_url": "https://kc.kobotoolbox.org/media/original?media_file=dariengap2021%2Fattachments%2Fbf9676788f314c00a984ea8002333ac1%2F5d24ca84-2a35-4076-9b31-f34c5feb7c0a%2F3a-16_2_36-20_16_34.jpg",
        "filename": "dariengap2021/attachments/bf9676788f314c00a984ea8002333ac1/5d24ca84-2a35-4076-9b31-f34c5feb7c0a/3a-16_2_36-20_16_34.jpg",
        "instance": 90570460,
        "download_medium_url": "https://kc.kobotoolbox.org/media/medium?media_file=dariengap2021%2Fattachments%2Fbf9676788f314c00a984ea8002333ac1%2F5d24ca84-2a35-4076-9b31-f34c5feb7c0a%2F3a-16_2_36-20_16_34.jpg",
        "id": 32010345,
        "xform": 639284
      }
    ],
    "Edited_date_and_time": "2019-07-16T15:08:00.000-05:00",
    "_status": "submitted_via_web",
    "formhub/uuid": "bf9676788f314c00a984ea8002333ac1",
    "username": "username not found",
    "_validation_status": {},
    "_uuid": "5d24ca84-2a35-4076-9b31-f34c5feb7c0a",
    "_submitted_by": null,
    "end": "2021-03-29T20:17:18.231-05:00",
    "group_ve9cv03/Site_name": "Fuerte de San Geronimo de Yaviza",
    "group_qk9bw75": [{
        "group_qk9bw75/Photo_1": "3a-16_2_36-20_16_34.jpg"
      },
      {
        "group_qk9bw75/Photo_1": "3b-16_2_40-20_17_7.jpg"
      }
    ],
    "What_did_you_find": "site",
    "__version__": "vJLQEGi5dLMUNuBsjGNRmu",
    "Edited_by": "1503628_CAL",
    "group_ve9cv03/Ground_visibility": "high",
    "_submission_time": "2021-03-30T01:18:42",
    "group_ve9cv03/Description_001": "unidentified/Fort is oriented to river -- 35 degrees NE? La provincia de Darien cuenta con Casas Fuertes, construidas por los espa침oles entre los a침os de 1760 a 1785, que estaban equipadas con ca침ones, protegidas por soldados y ten칤an como prop칩sito repeler los ataques ind칤genas, de corsarios, filibusteros y piratas, quienes constantemente atacban las poblaciones ocupadas por Espa침a durante la 칠poca del Virreinato de Nueva Granada. Uno de los fuertes construidos por los espa침oles es el Fuerte San Geronimo de Yaviza (r칤o Chucunaque), reconocido hoy d칤a como Patrimonio Hist칩rico de la Humanidad.",
    "_geolocation": [
      8.155743,
      -77.690395
    ],
    "deviceid": "ee.kobotoolbox.org:SamGhFwda0v8M1oh",
    "group_ve9cv03/Anthropological_disturbance": "construction__construcci_n",
    "_id": 90570460,
    "Record_your_current_location": "8.155743 -77.690395 0 0"
  }
]
